[{"event_id":"rfb-1","schema_version":"1.0.0","session_id":"test-pipeline-golden","t_ms":1000,"t_wall":"2026-01-01T00:00:01Z","event_type":"session.started","actor_type":"recorder","normalization_meta":{"sourceEventId":"rfb-1","sourceEventType":"session_start","normalizationRuleVersion":"1.0.0","redactionApplied":false}},{"event_id":"rfb-5","schema_version":"1.0.0","session_id":"test-pipeline-golden","t_ms":2000,"t_wall":"2026-01-01T00:00:02Z","event_type":"interaction.click","actor_type":"human","page_context":{"url":"https://app.example.com/settings","urlNormalized":"https://app.example.com/settings","domain":"app.example.com","routeTemplate":"/settings","pageTitle":"Settings","applicationLabel":"App"},"target_summary":{"selector":"#save-settings","selectorConfidence":1,"label":"Save Settings","isSensitive":false},"normalization_meta":{"sourceEventId":"rfb-5","sourceEventType":"click","normalizationRuleVersion":"1.0.0","redactionApplied":false}},{"event_id":"rfb-6","schema_version":"1.0.0","session_id":"test-pipeline-golden","t_ms":5000,"t_wall":"2026-01-01T00:00:05Z","event_type":"session.stopped","actor_type":"recorder","normalization_meta":{"sourceEventId":"rfb-6","sourceEventType":"session_stop","normalizationRuleVersion":"1.0.0","redactionApplied":false}}]